rest_api_client/__init__.py
rest_api_client/lib.py
py_rest_api_client-0.2.1.dist-info/LICENSE
py_rest_api_client-0.2.1.dist-info/METADATA
py_rest_api_client-0.2.1.dist-info/WHEEL
py_rest_api_client-0.2.1.dist-info/top_level.txt
py_rest_api_client-0.2.1.dist-info/RECORD
