Metadata-Version: 2.1
Name: py-rest-api-client
Version: 0.2.1
Summary: A
Home-page: https://github.com/paolorechia/rest-api-client
Author: Paolo Rechia
Author-email: paolorechia+pyrestapiclient@gmail.com
License: UNKNOWN
Project-URL: Bug Tracker, https://github.com/paolorechia/rest-api-client/issues
Platform: UNKNOWN
Classifier: Programming Language :: Python :: 3
Classifier: License :: OSI Approved :: MIT License
Classifier: Operating System :: OS Independent
Requires-Python: >=3.8
License-File: LICENSE
Requires-Dist: httpx (==0.18.2)
Requires-Dist: httpx-auth (==0.10.0)
Requires-Dist: pydantic (==1.8.2)
Requires-Dist: makefun (==1.11.3)
